load_environ_typed_kubernetes/__init__.py
load_environ_typed_kubernetes/loaders.py
load_environ_typed_kubernetes-0.0.1.dist-info/METADATA
load_environ_typed_kubernetes-0.0.1.dist-info/WHEEL
load_environ_typed_kubernetes-0.0.1.dist-info/licenses/LICENSE.txt
load_environ_typed_kubernetes-0.0.1.dist-info/RECORD
