Metadata-Version: 2.4
Name: load-environ-typed-kubernetes
Version: 0.0.1
Summary: Extends load-environ-typed to get info right from Kubernetes API
Project-URL: Homepage, https://github.com/jbwdevries/python-load-environ-typed-kubernetes
Project-URL: Bug Tracker, https://github.com/jbwdevries/python-load-environ-typed-kubernetes/issues
Author: Johan B.W. de Vries
License: Copyright (c) 2025, Johan B.W. de Vries
License-File: LICENSE.txt
Classifier: License :: OSI Approved :: MIT License
Classifier: Operating System :: OS Independent
Classifier: Programming Language :: Python :: 3
Requires-Python: >=3.8
Requires-Dist: kubernetes
